{
  "id": "w3-prove-end-to-end",
  "name": "w3-prove-end-to-end",
  "title": "Prove W3 end-to-end — host-agent judge contract + dogfood worked example",
  "description": "",
  "status": "completed",
  "dev_type": null,
  "scope": null,
  "package": null,
  "priority": "P2",
  "creator": "oydodo",
  "assignee": "oydodo",
  "createdAt": "2026-06-21",
  "completedAt": "2026-06-21",
  "branch": null,
  "base_branch": "main",
  "worktree_path": null,
  "commit": null,
  "pr_url": null,
  "subtasks": [],
  "children": [],
  "parent": null,
  "relatedFiles": [],
  "notes": "",
  "meta": {}
}