{
  "id": "design-codas-structure-map-schema",
  "name": "design-codas-structure-map-schema",
  "title": "Design Codas Structure Map Schema",
  "description": "",
  "status": "completed",
  "dev_type": "docs",
  "scope": null,
  "package": "codas",
  "priority": "P1",
  "creator": "oydodo",
  "assignee": "oydodo",
  "createdAt": "2026-06-17",
  "completedAt": "2026-06-17",
  "branch": null,
  "base_branch": "main",
  "worktree_path": null,
  "commit": null,
  "pr_url": null,
  "subtasks": [],
  "children": [],
  "parent": null,
  "relatedFiles": [],
  "notes": "",
  "meta": {}
}
